varaps/__init__.py
varaps/main.py
varaps/util/VariantsProportionCoOcc.py
varaps/util/VariantsProportionFreyja1Sparse.py
varaps/util/VariantsProportionFreyjaSparse.py
varaps/util/VariantsProportionLCS.py
varaps/util/downsampling.py
varaps/util/generate_M.py
varaps/util/get_mutations.py
varaps/util/helper_functions.py
varaps/util/mode1.py
varaps/util/mode2.py
varaps/util/parse_position.py
varaps/util/query_mutation_read.py
varaps/util/read_bam_file.py
varaps/util/refseq.py
varaps-1.2.0.dist-info/entry_points.txt
varaps-1.2.0.dist-info/LICENSE
varaps-1.2.0.dist-info/WHEEL
varaps-1.2.0.dist-info/METADATA
varaps-1.2.0.dist-info/RECORD
